my_package/__init__.py
my_package/linear_models.py
finance_ml_amoniz-0.3.0.dist-info/METADATA
finance_ml_amoniz-0.3.0.dist-info/WHEEL
finance_ml_amoniz-0.3.0.dist-info/RECORD
