Metadata-Version: 2.4
Name: finance-ml-amoniz
Version: 0.3.0
Summary: Projet d'exercice ML en finance
Author: antoine31
Author-email: antoine.moniz@dauphine.eu
Requires-Python: >=3.9
Classifier: Programming Language :: Python :: 3
Classifier: Programming Language :: Python :: 3.9
Classifier: Programming Language :: Python :: 3.10
Classifier: Programming Language :: Python :: 3.11
Classifier: Programming Language :: Python :: 3.12
Classifier: Programming Language :: Python :: 3.13
Classifier: Programming Language :: Python :: 3.14
Requires-Dist: numpy
